passbolt/__init__.py
passbolt/passbolt.py
passbolt-1.24.dist-info/LICENSE
passbolt-1.24.dist-info/METADATA
passbolt-1.24.dist-info/WHEEL
passbolt-1.24.dist-info/top_level.txt
passbolt-1.24.dist-info/RECORD
