Metadata-Version: 2.1
Name: passbolt
Version: 1.24
Summary: Passbolt python module
Home-page: https://github.com/daniel-lynch/passbolt
Author: Daniel Lynch
Author-email: daniel.lynch2016@gmail.com
License: MIT
Platform: UNKNOWN
Requires-Dist: argparse
Requires-Dist: python-gnupg
Requires-Dist: requests
